earthdata_varinfo-4.0.0.dist-info/licenses/LICENSE
varinfo/__init__.py
varinfo/attribute_container.py
varinfo/cf_config.py
varinfo/cmr_search.py
varinfo/exceptions.py
varinfo/generate_umm_var.py
varinfo/group.py
varinfo/umm_var.py
varinfo/utilities.py
varinfo/var_info.py
varinfo/variable.py
earthdata_varinfo-4.0.0.dist-info/METADATA
earthdata_varinfo-4.0.0.dist-info/WHEEL
earthdata_varinfo-4.0.0.dist-info/top_level.txt
earthdata_varinfo-4.0.0.dist-info/RECORD
