Metadata-Version: 2.4
Name: earthdata-varinfo
Version: 4.0.0
Summary: A package for parsing Earth Observation science granule structure and extracting relations between science variables and their associated metadata, such as coordinates.
Home-page: https://github.com/nasa/earthdata-varinfo
Author: NASA EOSDIS SDPS Data Services Team
Author-email: owen.m.littlejohns@nasa.gov
License: License :: OSI Approved :: Apache Software License
Classifier: Programming Language :: Python
Classifier: Programming Language :: Python :: 3
Classifier: Operating System :: OS Independent
Requires-Python: >=3.9
License-File: LICENSE
Requires-Dist: netCDF4>=1.7.2
Requires-Dist: numpy<2.3,>=1.24.2
Requires-Dist: python-cmr~=0.12.0
Requires-Dist: requests~=2.31.0
Requires-Dist: urllib3~=2.6.1
Provides-Extra: dev
Requires-Dist: ipython~=8.18.1; extra == "dev"
Requires-Dist: jsonschema~=4.23.0; extra == "dev"
Requires-Dist: pre-commit~=4.2.0; extra == "dev"
Requires-Dist: pycodestyle~=2.12.1; extra == "dev"
Requires-Dist: pylint~=3.3.6; extra == "dev"
Requires-Dist: pytest~=8.3.5; extra == "dev"
Requires-Dist: pytest-cov~=6.0.0; extra == "dev"
Dynamic: author
Dynamic: author-email
Dynamic: classifier
Dynamic: description
Dynamic: description-content-type
Dynamic: home-page
Dynamic: license
Dynamic: license-file
Dynamic: provides-extra
Dynamic: requires-dist
Dynamic: requires-python
Dynamic: summary
